{
  "id": "2026-06-18-expanded",
  "date": "2026-06-18",
  "title": "Daily Source Digest",
  "generatedAt": "2026-06-18T03:00:48.738240",
  "note": "Daily source-balanced news digest — morning update.",
  "updatedAt": "2026-06-18T03:00:48",
  "sections": [
    {
      "name": "World / Geopolitics",
      "stories": [
        {
          "title": "How Does Trump’s Iran Deal Compare To Obama’s? Here’s What We Know.",
          "summary": "How Does Trump’s Iran Deal Compare To Obama’s? Here’s What We Know..\n\nWhen Donald Trump launched his first presidential campaign, he pledged to withdraw the United States from the Joint Comprehensive Plan of Action, President Barack Obama’s nuclear agreement with Iran. Trump issued a statement condemning the JCPOA as “very dangerous” shortly after it was finalized on July 14, 2015.\n\nThe president never dropped his opposition, pulling out ... Al Jazeera: Trump accuses Obama of ‘bribing’ Iran in 2015 nuclear deal at G7 summit.\n\nAl Jazeera reports that uS President Donald Trump has accused his predecessor Barack Obama of ‘bribing’ Iran to agree to the 2015 nuclear deal.",
          "links": [
            {
              "url": "https://www.aljazeera.com/video/newsfeed/2026/6/17/trump-accuses-obama-of-bribing-iran-in-2015-nuclear-deal-at-g7-summit?traffic_source=rss",
              "source": "Al Jazeera",
              "headline": "Trump accuses Obama of ‘bribing’ Iran in 2015 nuclear deal at G7 summit",
              "excerpt": "US President Donald Trump has accused his predecessor Barack Obama of ‘bribing’ Iran to agree to the 2015 nuclear deal.",
              "imageUrl": "https://www.aljazeera.com/wp-content/uploads/2026/06/image-1781702439.jpg?resize=1920%2C1080&quality=80",
              "imageAlt": "Trump accuses Obama of ‘bribing’ Iran in 2015 nuclear deal at G7 summit",
              "outlet": "Al Jazeera",
              "sourceBias": "Lean Left",
              "sourceReliability": "medium",
              "bias": "Lean Left",
              "alignment": "Lean Left",
              "alignmentBasis": "source-default-fallback: no article alignment cues; source prior=Lean Left",
              "confidence": "medium",
              "reliability": "medium",
              "reliabilityBasis": "source-prior=medium; article-text: no reliability modifier cues",
              "ratingMethod": "deterministic-local-article-heuristic-v2"
            },
            {
              "url": "https://www.dailywire.com/news/how-does-trumps-iran-deal-compare-to-obamas-heres-what-we-know",
              "source": "Daily Wire",
              "headline": "How Does Trump’s Iran Deal Compare To Obama’s? Here’s What We Know.",
              "excerpt": "When Donald Trump launched his first presidential campaign, he pledged to withdraw the United States from the Joint Comprehensive Plan of Action, President Barack Obama’s nuclear agreement with Iran. Trump issued a statement condemning the JCPOA as “very dangerous” shortly after it was finalized on July 14, 2015. The president never dropped his opposition, pulling out ...",
              "imageUrl": "https://dw-wp-production.imgix.net/2026/06/Gemini_Generated_Image_t71sldt71sldt71s-1.png?ar=16%3A9&auto=compress&crop=faces&cs=origin&fit=crop&w=1200&h=800&ixlib=react-9.11.0",
              "imageAlt": "How Does Trump’s Iran Deal Compare To Obama’s? Here’s What We Know.",
              "outlet": "Daily Wire",
              "sourceBias": "Right",
              "sourceReliability": "medium",
              "bias": "Right",
              "alignment": "Right",
              "alignmentBasis": "source-default-fallback: no article alignment cues; source prior=Right",
              "confidence": "high",
              "reliability": "high",
              "reliabilityBasis": "source-prior=medium; article-text raises reliability: (data|study|report|filing|statement|interview|confirmed|verified)",
              "ratingMethod": "deterministic-local-article-heuristic-v2"
            }
          ],
          "summaryMethod": "deterministic-multi-source-mini-story-fallback-v1",
          "summaryFallbackReason": "lm-studio-summary-http-error: 400: {     \"error\": {         \"message\": \"No models loaded. Please load a model in the developer page or use the 'lms load' command.\",         \"type\":; retryError=lm-studio-summary-http-error: 400: {     \"error\": {         \"message\": \"No models loaded. Please load a mod; summaryBatchSize=1; chunkIndexes=[0]",
          "imageUrl": "https://www.aljazeera.com/wp-content/uploads/2026/06/image-1781702439.jpg?resize=1920%2C1080&quality=80",
          "imageAlt": "Trump accuses Obama of ‘bribing’ Iran in 2015 nuclear deal at G7 summit",
          "imageCredit": "Al Jazeera"
        },
        {
          "title": "Drones create the first-ever Fifa scoreboard in Seattle sky",
          "summary": "Drones create the first-ever Fifa scoreboard in Seattle sky. BBC reporter Max Matza is in Seattle, Washington, where 400 drones lit up the night sky on Monday to display the score of the Egypt v Belgium match.",
          "links": [
            {
              "url": "https://www.bbc.com/news/videos/ced4y9ljye9o?at_medium=RSS&at_campaign=rss",
              "source": "BBC World",
              "headline": "Drones create the first-ever Fifa scoreboard in Seattle sky",
              "excerpt": "BBC reporter Max Matza is in Seattle, Washington, where 400 drones lit up the night sky on Monday to display the score of the Egypt v Belgium match.",
              "imageUrl": "https://ichef.bbci.co.uk/ace/standard/240/cpsprodpb/12cb/live/82656b70-699e-11f1-b1db-af71d47507d6.jpg",
              "imageAlt": "Drones create the first-ever Fifa scoreboard in Seattle sky",
              "outlet": "BBC",
              "sourceBias": "Center",
              "sourceReliability": "high",
              "bias": "Center",
              "alignment": "Center",
              "alignmentBasis": "source-default-fallback: no article alignment cues; source prior=Center",
              "confidence": "high",
              "reliability": "high",
              "reliabilityBasis": "source-prior=high; article-text: no reliability modifier cues",
              "ratingMethod": "deterministic-local-article-heuristic-v2",
              "quality": "Public broadcaster"
            }
          ],
          "summaryMethod": "deterministic-multi-source-mini-story-fallback-v1",
          "summaryFallbackReason": "lm-studio-summary-http-error: 400: {     \"error\": {         \"message\": \"No models loaded. Please load a model in the developer page or use the 'lms load' command.\",         \"type\":; retryError=lm-studio-summary-http-error: 400: {     \"error\": {         \"message\": \"No models loaded. Please load a mod; summaryBatchSize=1; chunkIndexes=[1]",
          "imageUrl": "https://ichef.bbci.co.uk/ace/standard/240/cpsprodpb/12cb/live/82656b70-699e-11f1-b1db-af71d47507d6.jpg",
          "imageAlt": "Drones create the first-ever Fifa scoreboard in Seattle sky",
          "imageCredit": "BBC"
        },
        {
          "title": "Telegram challenges India ban over exam paper leak fears",
          "summary": "Telegram challenges India ban over exam paper leak fears. Telegram CEO Pavel Durov has called the ban a \"mistake\", arguing it would punish millions of users.\n\nAl Jazeera: Telegram challenges India app ban, calls move unconstitutional.\n\nAl Jazeera reports that india blocked Telegram after exam paper leaks, prompting the legal challenge.",
          "links": [
            {
              "url": "https://www.aljazeera.com/news/2026/6/17/telegram-challenges-india-app-ban-calls-move-unconstitutional?traffic_source=rss",
              "source": "Al Jazeera",
              "headline": "Telegram challenges India app ban, calls move unconstitutional",
              "excerpt": "India blocked Telegram after exam paper leaks, prompting the legal challenge.",
              "imageUrl": "https://www.aljazeera.com/wp-content/uploads/2026/06/reuters_6a32ad35-1781706037.jpg?resize=1920%2C1440",
              "imageAlt": "Telegram challenges India app ban, calls move unconstitutional",
              "outlet": "Al Jazeera",
              "sourceBias": "Lean Left",
              "sourceReliability": "medium",
              "bias": "Lean Left",
              "alignment": "Lean Left",
              "alignmentBasis": "source-default-fallback: no article alignment cues; source prior=Lean Left",
              "confidence": "medium",
              "reliability": "medium",
              "reliabilityBasis": "source-prior=medium; article-text: no reliability modifier cues",
              "ratingMethod": "deterministic-local-article-heuristic-v2"
            },
            {
              "url": "https://www.bbc.com/news/articles/c4gy40q8wz0o?at_medium=RSS&at_campaign=rss",
              "source": "BBC World",
              "headline": "Telegram challenges India ban over exam paper leak fears",
              "excerpt": "Telegram CEO Pavel Durov has called the ban a \"mistake\", arguing it would punish millions of users.",
              "imageUrl": "https://ichef.bbci.co.uk/ace/standard/240/cpsprodpb/a9a1/live/40f11710-6a17-11f1-b107-6ded809b7b86.jpg",
              "imageAlt": "Telegram challenges India ban over exam paper leak fears",
              "outlet": "BBC",
              "sourceBias": "Center",
              "sourceReliability": "high",
              "bias": "Company",
              "alignment": "Company",
              "alignmentBasis": "article-text: company provenance cue(s): (ceo|founder|investors|funding round|acquisition|merger)",
              "confidence": "high",
              "reliability": "high",
              "reliabilityBasis": "source-prior=high; article-text: no reliability modifier cues",
              "ratingMethod": "deterministic-local-article-heuristic-v2",
              "quality": "Public broadcaster"
            }
          ],
          "summaryMethod": "deterministic-multi-source-mini-story-fallback-v1",
          "summaryFallbackReason": "lm-studio-summary-http-error: 400: {     \"error\": {         \"message\": \"No models loaded. Please load a model in the developer page or use the 'lms load' command.\",         \"type\":; retryError=lm-studio-summary-http-error: 400: {     \"error\": {         \"message\": \"No models loaded. Please load a mod; summaryBatchSize=1; chunkIndexes=[2]",
          "imageUrl": "https://www.aljazeera.com/wp-content/uploads/2026/06/reuters_6a32ad35-1781706037.jpg?resize=1920%2C1440",
          "imageAlt": "Telegram challenges India app ban, calls move unconstitutional",
          "imageCredit": "Al Jazeera"
        },
        {
          "title": "Comedian Nate Bargatze draws fan backlash after attending Trump's White House UFC event",
          "summary": "Comedian Nate Bargatze draws fan backlash after attending Trump's White House UFC event. Comedian Nate Bargatze is facing a wave of criticism from fans after he was spotted at the UFC Freedom 250 event held on the South Lawn of the White House on Sunday, which coincided with President Trump's 80th birthday and drew more than 4,000 attendees.\n\nA rep for Bargatze said that the comedian \"is not political nor is anything he produces\" and described him as a \"huge UFC fan\" who has followed the sport \"since before it became political.\". Breitbart: Comedian Nate Bargatze Faces Fan Backlash After Attending Trump's UFC White House Event.\n\nBreitbart reports that comedian Nate Bargatze is facing backlash from fans after attending President Donald Trump's White House UFC event on Sunday. \"I'm heartbroken that I can't be a fan anymore,\" one person bemoaned.\n\nThe post Comedian Nate Bargatze Faces Fan B",
          "links": [
            {
              "url": "https://www.breitbart.com/entertainment/2026/06/17/comedian-nate-bargatze-faces-fan-backlash-after-attending-trumps-ufc-white-house-event/",
              "source": "Breitbart",
              "headline": "Comedian Nate Bargatze Faces Fan Backlash After Attending Trump's UFC White House Event",
              "excerpt": "Comedian Nate Bargatze is facing backlash from fans after attending President Donald Trump's White House UFC event on Sunday. \"I'm heartbroken that I can't be a fan anymore,\" one person bemoaned. The post Comedian Nate Bargatze Faces Fan Backlash After Attending Trump’s UFC White House Event appeared first on <a rel=\"nof",
              "imageUrl": "https://media.breitbart.com/media/2026/06/NateBargatze-640x335.jpg",
              "imageAlt": "Comedian Nate Bargatze Faces Fan Backlash After Attending Trump's UFC White House Event",
              "outlet": "Breitbart",
              "sourceBias": "Right",
              "sourceReliability": "low",
              "bias": "Right",
              "alignment": "Right",
              "alignmentBasis": "source-default-fallback: no article alignment cues; source prior=Right",
              "confidence": "low",
              "reliability": "low",
              "reliabilityBasis": "source-prior=low; article-text: no reliability modifier cues",
              "ratingMethod": "deterministic-local-article-heuristic-v2"
            },
            {
              "url": "https://www.washingtontimes.com/news/2026/jun/17/comedian-nate-bargatze-draws-fan-backlash-attending-trumps-white/",
              "source": "Washington Times",
              "headline": "Comedian Nate Bargatze draws fan backlash after attending Trump's White House UFC event",
              "excerpt": "Comedian Nate Bargatze is facing a wave of criticism from fans after he was spotted at the UFC Freedom 250 event held on the South Lawn of the White House on Sunday, which coincided with President Trump's 80th birthday and drew more than 4,000 attendees. A rep for Bargatze said that the comedian \"is not political nor is anything he produces\" and described him as a \"huge UFC fan\" who has followed the sport \"since before it became political.\"",
              "imageUrl": "https://twt-thumbs.washtimes.com/media/image/2026/02/15/NASCAR_Daytona_500_Bargatze_Auto_Racing_53993_s1440x960.jpg?f72536d07237fdd262042ae8f5e6e6de3b865f3c",
              "imageAlt": "Comedian Nate Bargatze draws fan backlash after attending Trump's White House UFC event",
              "outlet": "Washington Times",
              "sourceBias": "Lean Right",
              "sourceReliability": "medium",
              "bias": "Lean Right",
              "alignment": "Lean Right",
              "alignmentBasis": "source-default-fallback: no article alignment cues; source prior=Lean Right",
              "confidence": "medium",
              "reliability": "medium",
              "reliabilityBasis": "source-prior=medium; article-text: no reliability modifier cues",
              "ratingMethod": "deterministic-local-article-heuristic-v2"
            }
          ],
          "summaryMethod": "deterministic-multi-source-mini-story-fallback-v1",
          "summaryFallbackReason": "lm-studio-summary-http-error: 400: {     \"error\": {         \"message\": \"No models loaded. Please load a model in the developer page or use the 'lms load' command.\",         \"type\":; retryError=lm-studio-summary-http-error: 400: {     \"error\": {         \"message\": \"No models loaded. Please load a mod; summaryBatchSize=1; chunkIndexes=[3]",
          "imageUrl": "https://media.breitbart.com/media/2026/06/NateBargatze-640x335.jpg",
          "imageAlt": "Comedian Nate Bargatze Faces Fan Backlash After Attending Trump's UFC White House Event",
          "imageCredit": "Breitbart"
        },
        {
          "title": "Backlash Mounts Against MLB For Targeting Christians: ‘You’ll Be Hearing From My Office’",
          "summary": "Backlash Mounts Against MLB For Targeting Christians: ‘You’ll Be Hearing From My Office’. Backlash against Major League Baseball is continuing to build after the league condemned and warned Christian baseball players for counter-signaling or outright rejecting an LGBT “Pride Night” last week.\n\nAs highlighted by The Daily Wire, several San Francisco Giants players marked their gay pride-themed baseball caps with Bible passages, while another player refused to wear ... Washington Times: MLB 'must answer' for warning after Giants pitchers' Pride Night message: Sen. Hawley.\n\nWashington Times reports that sen. Josh Hawley sent a letter to MLB Commissioner Rob Manfred on Tuesday demanding answers after the league issued a warning to three San Francisco Giants pitchers who wrote a Bible passage on their caps for the team's LGBTQ Pride night on Friday.",
          "links": [
            {
              "url": "https://www.dailywire.com/news/backlash-mounts-against-mlb-for-targeting-christians-youll-be-hearing-from-my-office",
              "source": "Daily Wire",
              "headline": "Backlash Mounts Against MLB For Targeting Christians: ‘You’ll Be Hearing From My Office’",
              "excerpt": "Backlash against Major League Baseball is continuing to build after the league condemned and warned Christian baseball players for counter-signaling or outright rejecting an LGBT “Pride Night” last week. As highlighted by The Daily Wire, several San Francisco Giants players marked their gay pride-themed baseball caps with Bible passages, while another player refused to wear ...",
              "imageUrl": "https://dw-wp-production.imgix.net/2026/06/GettyImages-2281423727.jpg?ar=16%3A9&auto=compress&crop=faces&cs=origin&fit=crop&w=1200&h=800&ixlib=react-9.11.0",
              "imageAlt": "Backlash Mounts Against MLB For Targeting Christians: ‘You’ll Be Hearing From My Office’",
              "outlet": "Daily Wire",
              "sourceBias": "Right",
              "sourceReliability": "medium",
              "bias": "Right",
              "alignment": "Right",
              "alignmentBasis": "source-default-fallback: no article alignment cues; source prior=Right",
              "confidence": "medium",
              "reliability": "medium",
              "reliabilityBasis": "source-prior=medium; article-text: no reliability modifier cues",
              "ratingMethod": "deterministic-local-article-heuristic-v2"
            },
            {
              "url": "https://www.washingtontimes.com/news/2026/jun/17/mlb-must-answer-warning-giants-pitchers-pride-night-message-sen-josh/",
              "source": "Washington Times",
              "headline": "MLB 'must answer' for warning after Giants pitchers' Pride Night message: Sen. Hawley",
              "excerpt": "Sen. Josh Hawley sent a letter to MLB Commissioner Rob Manfred on Tuesday demanding answers after the league issued a warning to three San Francisco Giants pitchers who wrote a Bible passage on their caps for the team's LGBTQ Pride night on Friday.",
              "imageUrl": "https://twt-thumbs.washtimes.com/media/image/2026/02/10/Senate_Artic_Frost_27953_s1440x960.jpg?f72536d07237fdd262042ae8f5e6e6de3b865f3c",
              "imageAlt": "MLB 'must answer' for warning after Giants pitchers' Pride Night message: Sen. Hawley",
              "outlet": "Washington Times",
              "sourceBias": "Lean Right",
              "sourceReliability": "medium",
              "bias": "Lean Right",
              "alignment": "Lean Right",
              "alignmentBasis": "source-default-fallback: no article alignment cues; source prior=Lean Right",
              "confidence": "medium",
              "reliability": "medium",
              "reliabilityBasis": "source-prior=medium; article-text: no reliability modifier cues",
              "ratingMethod": "deterministic-local-article-heuristic-v2"
            }
          ],
          "summaryMethod": "deterministic-multi-source-mini-story-fallback-v1",
          "summaryFallbackReason": "lm-studio-summary-http-error: 400: {     \"error\": {         \"message\": \"No models loaded. Please load a model in the developer page or use the 'lms load' command.\",         \"type\":; retryError=lm-studio-summary-http-error: 400: {     \"error\": {         \"message\": \"No models loaded. Please load a mod; summaryBatchSize=1; chunkIndexes=[4]",
          "imageUrl": "https://dw-wp-production.imgix.net/2026/06/GettyImages-2281423727.jpg?ar=16%3A9&auto=compress&crop=faces&cs=origin&fit=crop&w=1200&h=800&ixlib=react-9.11.0",
          "imageAlt": "Backlash Mounts Against MLB For Targeting Christians: ‘You’ll Be Hearing From My Office’",
          "imageCredit": "Daily Wire"
        },
        {
          "title": "Warsh-led Fed holds rates steady, as inflation rules out easing sought by Trump",
          "summary": "Warsh-led Fed holds rates steady, as inflation rules out easing sought by Trump. The Federal Reserve voted Wednesday to hold its interest rate target steady following the first meeting for new Fed Chairman Kevin Warsh, meaning that President Donald Trump’s long-expressed desire for the central bank to lower interest rates will be unfulfilled for now.\n\nAfter a two-day meeting in Washington, the Fed’s monetary policy committee announced it […]. New York Post: Fed holds interest rates steady in Kevin Warsh’s first meeting as chair.\n\nNew York Post reports that the Federal Reserve held interest rates steady at Kevin Warsh’s first meeting as chairman Wednesday in a unanimous vote.",
          "links": [
            {
              "url": "https://nypost.com/2026/06/17/business/fed-holds-interest-rates-steady-in-kevin-warshs-first-meeting-as-chair/",
              "source": "New York Post",
              "headline": "Fed holds interest rates steady in Kevin Warsh’s first meeting as chair",
              "excerpt": "The Federal Reserve held interest rates steady at Kevin Warsh’s first meeting as chairman Wednesday in a unanimous vote.",
              "imageUrl": "https://nypost.com/wp-content%2Fuploads%2Fsites%2F2%2F2026%2F06%2Fkevin-warsh-looked-swearing-in-128509837.jpg?w%3D1024",
              "imageAlt": "Fed holds interest rates steady in Kevin Warsh’s first meeting as chair",
              "outlet": "New York Post",
              "sourceBias": "Right",
              "sourceReliability": "medium",
              "bias": "Right",
              "alignment": "Right",
              "alignmentBasis": "source-default-fallback: no article alignment cues; source prior=Right",
              "confidence": "medium",
              "reliability": "medium",
              "reliabilityBasis": "source-prior=medium; article-text: no reliability modifier cues",
              "ratingMethod": "deterministic-local-article-heuristic-v2"
            },
            {
              "url": "https://www.washingtonexaminer.com/policy/finance-and-economy/4612574/warsh-fed-rates-steady-inflation-trump/",
              "source": "Washington Examiner",
              "headline": "Warsh-led Fed holds rates steady, as inflation rules out easing sought by Trump",
              "excerpt": "The Federal Reserve voted Wednesday to hold its interest rate target steady following the first meeting for new Fed Chairman Kevin Warsh, meaning that President Donald Trump’s long-expressed desire for the central bank to lower interest rates will be unfulfilled for now. After a two-day meeting in Washington, the Fed’s monetary policy committee announced it […]",
              "imageUrl": "https://www.washingtonexaminer.com/wp-content/uploads/2026/06/warsh.jpg?w=696",
              "imageAlt": "Warsh-led Fed holds rates steady, as inflation rules out easing sought by Trump",
              "outlet": "Washington Examiner",
              "sourceBias": "Lean Right",
              "sourceReliability": "medium",
              "bias": "Lean Right",
              "alignment": "Lean Right",
              "alignmentBasis": "source-default-fallback: no article alignment cues; source prior=Lean Right",
              "confidence": "medium",
              "reliability": "medium",
              "reliabilityBasis": "source-prior=medium; article-text: no reliability modifier cues",
              "ratingMethod": "deterministic-local-article-heuristic-v2"
            }
          ],
          "summaryMethod": "deterministic-multi-source-mini-story-fallback-v1",
          "summaryFallbackReason": "lm-studio-summary-http-error: 400: {     \"error\": {         \"message\": \"No models loaded. Please load a model in the developer page or use the 'lms load' command.\",         \"type\":; retryError=lm-studio-summary-http-error: 400: {     \"error\": {         \"message\": \"No models loaded. Please load a mod; summaryBatchSize=1; chunkIndexes=[5]",
          "imageUrl": "https://nypost.com/wp-content%2Fuploads%2Fsites%2F2%2F2026%2F06%2Fkevin-warsh-looked-swearing-in-128509837.jpg?w%3D1024",
          "imageAlt": "Fed holds interest rates steady in Kevin Warsh’s first meeting as chair",
          "imageCredit": "New York Post"
        },
        {
          "title": "White House Denies 'Leaked' Text of Iran Deal: 'Does Not Reflect' Agreement",
          "summary": "White House Denies 'Leaked' Text of Iran Deal: 'Does Not Reflect' Agreement. White House Communications Director Steven Cheung denied that a text circulating in multiple mainstream media outlets late on Tuesday was an accurate text of the ultimate draft of a memorandum of understanding between Iran and America to end the current war and pave the wave for nuclear negotiations.\n\nThe post White House Denies ‘Leaked’ Text. Daily Wire: Read Exactly What The White House Says Is In The Deal With Iran.\n\nDaily Wire reports that wASHINGTON— The text of the agreement between the United States and Iran has finally been shared with reporters.\n\nAfter days of intense scrutiny and debate over the deal, a senior Trump administration official read the “memorandum of understanding between the United States of America and the Islamic Republic of Iran” to reporters on a Wednesday afternoon ...",
          "links": [
            {
              "url": "https://www.breitbart.com/middle-east/2026/06/17/white-house-denies-leaked-text-of-iran-deal-does-not-reflect-agreement/",
              "source": "Breitbart",
              "headline": "White House Denies 'Leaked' Text of Iran Deal: 'Does Not Reflect' Agreement",
              "excerpt": "White House Communications Director Steven Cheung denied that a text circulating in multiple mainstream media outlets late on Tuesday was an accurate text of the ultimate draft of a memorandum of understanding between Iran and America to end the current war and pave the wave for nuclear negotiations. The post White House Denies ‘Leaked’ Text",
              "imageUrl": "https://media.breitbart.com/media/2026/06/GettyImages-2199937948-640x335.png",
              "imageAlt": "White House Denies 'Leaked' Text of Iran Deal: 'Does Not Reflect' Agreement",
              "outlet": "Breitbart",
              "sourceBias": "Right",
              "sourceReliability": "low",
              "bias": "Right",
              "alignment": "Right",
              "alignmentBasis": "source-default-fallback: no article alignment cues; source prior=Right",
              "confidence": "low",
              "reliability": "low",
              "reliabilityBasis": "source-prior=low; article-text: no reliability modifier cues",
              "ratingMethod": "deterministic-local-article-heuristic-v2"
            },
            {
              "url": "https://www.dailywire.com/news/read-exactly-what-the-white-house-says-is-in-the-deal-with-iran",
              "source": "Daily Wire",
              "headline": "Read Exactly What The White House Says Is In The Deal With Iran",
              "excerpt": "WASHINGTON— The text of the agreement between the United States and Iran has finally been shared with reporters. After days of intense scrutiny and debate over the deal, a senior Trump administration official read the “memorandum of understanding between the United States of America and the Islamic Republic of Iran” to reporters on a Wednesday afternoon ...",
              "imageUrl": "https://dw-wp-production.imgix.net/2026/06/Untitled-design-2026-06-17T123134.391.jpg?ar=16%3A9&auto=compress&crop=faces&cs=origin&fit=crop&w=1200&h=800&ixlib=react-9.11.0",
              "imageAlt": "Read Exactly What The White House Says Is In The Deal With Iran",
              "outlet": "Daily Wire",
              "sourceBias": "Right",
              "sourceReliability": "medium",
              "bias": "Right",
              "alignment": "Right",
              "alignmentBasis": "source-default-fallback: no article alignment cues; source prior=Right",
              "confidence": "medium",
              "reliability": "medium",
              "reliabilityBasis": "source-prior=medium; article-text: no reliability modifier cues",
              "ratingMethod": "deterministic-local-article-heuristic-v2"
            }
          ],
          "summaryMethod": "deterministic-multi-source-mini-story-fallback-v1",
          "summaryFallbackReason": "lm-studio-summary-http-error: 400: {     \"error\": {         \"message\": \"No models loaded. Please load a model in the developer page or use the 'lms load' command.\",         \"type\":; retryError=lm-studio-summary-http-error: 400: {     \"error\": {         \"message\": \"No models loaded. Please load a mod; summaryBatchSize=1; chunkIndexes=[6]",
          "imageUrl": "https://media.breitbart.com/media/2026/06/GettyImages-2199937948-640x335.png",
          "imageAlt": "White House Denies 'Leaked' Text of Iran Deal: 'Does Not Reflect' Agreement",
          "imageCredit": "Breitbart"
        }
      ]
    },
    {
      "name": "Australia",
      "stories": [
        {
          "title": "Canberra’s obscene compassion machine",
          "summary": "Canberra’s obscene compassion machine. The alleged abduction and murder of five-year-old Kumanjayi Little Baby from an Alice Springs town camp should have shattered one… The post Canberra’s obscene compassion machine appeared first on The Spectator Australia .\n\nWhat to read next: <a href=\"https://www.spectator.com.au/2026/06/jim-chalmers-is-one-of-the-most-u.",
          "links": [
            {
              "url": "https://www.spectator.com.au/2026/06/canberras-obscene-compassion-machine/",
              "source": "Spectator Australia",
              "headline": "Canberra’s obscene compassion machine",
              "excerpt": "The alleged abduction and murder of five-year-old Kumanjayi Little Baby from an Alice Springs town camp should have shattered one… The post Canberra’s obscene compassion machine appeared first on The Spectator Australia . What to read next: <a href=\"https://www.spectator.com.au/2026/06/jim-chalmers-is-one-of-the-most-u",
              "imageUrl": "https://www.spectator.com.au/wp-content/uploads/2026/06/swan_20_june_post.jpg",
              "imageAlt": "Canberra’s obscene compassion machine",
              "outlet": "Spectator Australia",
              "sourceBias": "Lean Right",
              "sourceReliability": "medium",
              "bias": "Lean Right",
              "alignment": "Lean Right",
              "alignmentBasis": "source-default-fallback: no article alignment cues; source prior=Lean Right",
              "confidence": "medium",
              "reliability": "medium",
              "reliabilityBasis": "source-prior=medium; article-text: no reliability modifier cues",
              "ratingMethod": "deterministic-local-article-heuristic-v2"
            }
          ],
          "summaryMethod": "deterministic-multi-source-mini-story-fallback-v1",
          "summaryFallbackReason": "lm-studio-summary-http-error: 400: {     \"error\": {         \"message\": \"No models loaded. Please load a model in the developer page or use the 'lms load' command.\",         \"type\":; retryError=lm-studio-summary-http-error: 400: {     \"error\": {         \"message\": \"No models loaded. Please load a mod; summaryBatchSize=1; chunkIndexes=[7]",
          "imageUrl": "https://www.spectator.com.au/wp-content/uploads/2026/06/swan_20_june_post.jpg",
          "imageAlt": "Canberra’s obscene compassion machine",
          "imageCredit": "Spectator Australia"
        },
        {
          "title": "Legal aid worker caught in bed with fugitive teen killer pleads guilty",
          "summary": "Legal aid worker caught in bed with fugitive teen killer pleads guilty. A 37-year-old legal aid worker who was arrested while sharing a hotel bed with a teenage killer she helped evade authorities after he breached his parole has pleaded guilty to attempting to pervert the course of justice.",
          "links": [
            {
              "url": "https://www.abc.net.au/news/2026-06-17/samantha-alampi-guilty-of-helping-fugitive-killer-flee-parole/106810436",
              "source": "ABC Australia",
              "headline": "Legal aid worker caught in bed with fugitive teen killer pleads guilty",
              "excerpt": "A 37-year-old legal aid worker who was arrested while sharing a hotel bed with a teenage killer she helped evade authorities after he breached his parole has pleaded guilty to attempting to pervert the course of justice.",
              "imageUrl": "https://live-production.wcms.abc-cdn.net.au/a84872b740406d5c4df8473a8811f957?impolicy=wcms_crop_resize&cropH=271&cropW=482&xPos=0&yPos=4&width=862&height=485",
              "imageAlt": "Legal aid worker caught in bed with fugitive teen killer pleads guilty",
              "outlet": "ABC News",
              "sourceBias": "Center",
              "sourceReliability": "high",
              "bias": "Center",
              "alignment": "Center",
              "alignmentBasis": "source-default-fallback: no article alignment cues; source prior=Center",
              "confidence": "high",
              "reliability": "high",
              "reliabilityBasis": "source-prior=high; article-text: no reliability modifier cues",
              "ratingMethod": "deterministic-local-article-heuristic-v2",
              "quality": "Public broadcaster"
            }
          ],
          "summaryMethod": "deterministic-multi-source-mini-story-fallback-v1",
          "summaryFallbackReason": "lm-studio-summary-http-error: 400: {     \"error\": {         \"message\": \"No models loaded. Please load a model in the developer page or use the 'lms load' command.\",         \"type\":; retryError=lm-studio-summary-http-error: 400: {     \"error\": {         \"message\": \"No models loaded. Please load a mod; summaryBatchSize=1; chunkIndexes=[8]",
          "imageUrl": "https://live-production.wcms.abc-cdn.net.au/a84872b740406d5c4df8473a8811f957?impolicy=wcms_crop_resize&cropH=271&cropW=482&xPos=0&yPos=4&width=862&height=485",
          "imageAlt": "Legal aid worker caught in bed with fugitive teen killer pleads guilty",
          "imageCredit": "ABC News"
        },
        {
          "title": "Pauline Hanson responds to Guardian journalist’s press club question with personal attack – video",
          "summary": "Pauline Hanson responds to Guardian journalist’s press club question with personal attack – video. Following senator Pauline Hanson’s address at the National Press Club, Guardian Australia senior reporter Sarah Martin asks Hanson about her daughter, Lee Hanson: ‘Taxpayers are paying more than $150,000 a year for your daughter to seemingly campaign full-time in Tasmania, while employed as a political adviser for a New South Wales senator.\n\nDid you have any role in appointing her to that position?’ Hanson accuses Martin of having an ‘obsession’ with her, her party and Gina Rinehart. Hanson sa.",
          "links": [
            {
              "url": "https://www.theguardian.com/australia-news/video/2026/jun/17/pauline-hanson-responds-to-guardian-journalists-press-club-question-with-personal-attack-video-ntwnfb",
              "source": "The Guardian Australia",
              "headline": "Pauline Hanson responds to Guardian journalist’s press club question with personal attack – video",
              "excerpt": "Following senator Pauline Hanson’s address at the National Press Club, Guardian Australia senior reporter Sarah Martin asks Hanson about her daughter, Lee Hanson: ‘Taxpayers are paying more than $150,000 a year for your daughter to seemingly campaign full-time in Tasmania, while employed as a political adviser for a New South Wales senator. Did you have any role in appointing her to that position?’ Hanson accuses Martin of having an ‘obsession’ with her, her party and Gina Rinehart. Hanson sa",
              "imageUrl": "https://i.guim.co.uk/img/media/61b5f1e96b75753c44be4204a41c4b938f4dd103/419_0_4186_3349/master/4186.jpg?width=140&quality=85&auto=format&fit=max&s=63fbf25587897027698b97f0ab9ee488",
              "imageAlt": "Pauline Hanson responds to Guardian journalist’s press club question with personal attack – video",
              "outlet": "The Guardian",
              "sourceBias": "Lean Left",
              "sourceReliability": "high",
              "bias": "Lean Left",
              "alignment": "Lean Left",
              "alignmentBasis": "source-default-fallback: no article alignment cues; source prior=Lean Left",
              "confidence": "high",
              "reliability": "high",
              "reliabilityBasis": "source-prior=high; article-text: no reliability modifier cues",
              "ratingMethod": "deterministic-local-article-heuristic-v2"
            }
          ],
          "summaryMethod": "deterministic-multi-source-mini-story-fallback-v1",
          "summaryFallbackReason": "lm-studio-summary-http-error: 400: {     \"error\": {         \"message\": \"No models loaded. Please load a model in the developer page or use the 'lms load' command.\",         \"type\":; retryError=lm-studio-summary-http-error: 400: {     \"error\": {         \"message\": \"No models loaded. Please load a mod; summaryBatchSize=1; chunkIndexes=[9]",
          "imageUrl": "https://i.guim.co.uk/img/media/61b5f1e96b75753c44be4204a41c4b938f4dd103/419_0_4186_3349/master/4186.jpg?width=140&quality=85&auto=format&fit=max&s=63fbf25587897027698b97f0ab9ee488",
          "imageAlt": "Pauline Hanson responds to Guardian journalist’s press club question with personal attack – video",
          "imageCredit": "The Guardian"
        },
        {
          "title": "Trump is in a sea of trouble over Iran",
          "summary": "Trump is in a sea of trouble over Iran. Donald Trump is engaged in one of the biggest battles of his career.\n\nAfter spending millions turning the Lincoln Memorial… The post Trump is in a sea of trouble over Iran appeared first on The Spectator Australia .\n\nWhat to read next: <a href=\"https://www.spectator.com.au/2026/06/trump-can-forge-a-lasting-peace-in-ira. Spectator Australia: It was inevitable that Prince George would go to Eton.\n\nSpectator Australia reports that it was, in the end, inevitable. Kensington Palace confirmed yesterday that Prince George will go to Eton in September.\n\nThere… The post It was inevitable that Prince George would go to Eton appeared first on The Spectator Australia . What to read next: <a href=\"https://www.spectator.com.au/2026/06/rache.",
          "links": [
            {
              "url": "https://www.spectator.com.au/2026/06/it-was-inevitable-that-prince-george-would-go-to-eton/",
              "source": "Spectator Australia",
              "headline": "It was inevitable that Prince George would go to Eton",
              "excerpt": "It was, in the end, inevitable. Kensington Palace confirmed yesterday that Prince George will go to Eton in September. There… The post It was inevitable that Prince George would go to Eton appeared first on The Spectator Australia . What to read next: <a href=\"https://www.spectator.com.au/2026/06/rache",
              "imageUrl": "https://www.spectator.com.au/wp-content/uploads/2026/06/GettyImages_2215020013_e1781673207992.jpg",
              "imageAlt": "It was inevitable that Prince George would go to Eton",
              "outlet": "Spectator Australia",
              "sourceBias": "Lean Right",
              "sourceReliability": "medium",
              "bias": "Lean Right",
              "alignment": "Lean Right",
              "alignmentBasis": "source-default-fallback: no article alignment cues; source prior=Lean Right",
              "confidence": "high",
              "reliability": "high",
              "reliabilityBasis": "source-prior=medium; article-text raises reliability: (data|study|report|filing|statement|interview|confirmed|verified)",
              "ratingMethod": "deterministic-local-article-heuristic-v2"
            }
          ],
          "summaryMethod": "deterministic-multi-source-mini-story-fallback-v1",
          "summaryFallbackReason": "lm-studio-summary-http-error: 400: {     \"error\": {         \"message\": \"No models loaded. Please load a model in the developer page or use the 'lms load' command.\",         \"type\":; retryError=lm-studio-summary-http-error: 400: {     \"error\": {         \"message\": \"No models loaded. Please load a mod; summaryBatchSize=1; chunkIndexes=[10]",
          "imageUrl": "https://www.spectator.com.au/wp-content/uploads/2026/06/GettyImages_2215020013_e1781673207992.jpg",
          "imageAlt": "It was inevitable that Prince George would go to Eton",
          "imageCredit": "Spectator Australia"
        }
      ]
    },
    {
      "name": "Technology",
      "stories": [
        {
          "title": "Two Stanford grads raise $11M to build a noninvasive wearable for hormone tracking",
          "summary": "Two Stanford grads raise $11M to build a noninvasive wearable for hormone tracking. Clair Health will track inflammation and bloating markers, energy levels, and cycle phase classification to give insights into cycle irregularities and perimenopause, as well as hormonal fluctuations, and how to navigate those changes.",
          "links": [
            {
              "url": "https://techcrunch.com/2026/06/17/two-stanford-grads-raise-11m-to-build-a-noninvasive-wearable-for-hormone-tracking/",
              "source": "TechCrunch",
              "headline": "Two Stanford grads raise $11M to build a noninvasive wearable for hormone tracking",
              "excerpt": "Clair Health will track inflammation and bloating markers, energy levels, and cycle phase classification to give insights into cycle irregularities and perimenopause, as well as hormonal fluctuations, and how to navigate those changes.",
              "imageUrl": "https://techcrunch.com/wp-content/uploads/2026/06/Clair-Wearable.jpg?resize=1200,750",
              "imageAlt": "Two Stanford grads raise $11M to build a noninvasive wearable for hormone tracking",
              "outlet": "TechCrunch",
              "sourceBias": "Center",
              "sourceReliability": "medium",
              "bias": "Center",
              "alignment": "Center",
              "alignmentBasis": "source-default-fallback: no article alignment cues; source prior=Center",
              "confidence": "medium",
              "reliability": "medium",
              "reliabilityBasis": "source-prior=medium; article-text: no reliability modifier cues",
              "ratingMethod": "deterministic-local-article-heuristic-v2"
            }
          ],
          "summaryMethod": "deterministic-multi-source-mini-story-fallback-v1",
          "summaryFallbackReason": "lm-studio-summary-http-error: 400: {     \"error\": {         \"message\": \"No models loaded. Please load a model in the developer page or use the 'lms load' command.\",         \"type\":; retryError=lm-studio-summary-http-error: 400: {     \"error\": {         \"message\": \"No models loaded. Please load a mod; summaryBatchSize=1; chunkIndexes=[11]",
          "imageUrl": "https://techcrunch.com/wp-content/uploads/2026/06/Clair-Wearable.jpg?resize=1200,750",
          "imageAlt": "Two Stanford grads raise $11M to build a noninvasive wearable for hormone tracking",
          "imageCredit": "TechCrunch"
        },
        {
          "title": "UFC 6 review: a bloody, brilliant MMA fighting game",
          "summary": "UFC 6 review: a bloody, brilliant MMA fighting game. PlayStation 5, Xbox Series X/S; EA Vancouver/Electronic Arts Micromanaging your fighter is a little tedious, but the action is thrilling in this authentically detailed sporting simulation Becoming a professional fighter takes years of repetition, drilling techniques and training footwork until everything is instinctual.\n\nYour body needs an automatic answer for every limb, from every angle. In MMA, which encompasses every martial art, it’s even harder.\n\nEA Sports’.",
          "links": [
            {
              "url": "https://www.theguardian.com/games/2026/jun/17/ufc-6-review-mma-fighting-game-ea-sports",
              "source": "The Guardian Technology",
              "headline": "UFC 6 review: a bloody, brilliant MMA fighting game",
              "excerpt": "PlayStation 5, Xbox Series X/S; EA Vancouver/Electronic Arts Micromanaging your fighter is a little tedious, but the action is thrilling in this authentically detailed sporting simulation Becoming a professional fighter takes years of repetition, drilling techniques and training footwork until everything is instinctual. Your body needs an automatic answer for every limb, from every angle. In MMA, which encompasses every martial art, it’s even harder. EA Sports’",
              "imageUrl": "https://i.guim.co.uk/img/media/cbe331faa3d00be216f17783e27b0d3f588f3678/202_0_1767_1414/master/1767.jpg?width=140&quality=85&auto=format&fit=max&s=eedf5bbad37333eab990324e08ee1783",
              "imageAlt": "UFC 6 review: a bloody, brilliant MMA fighting game",
              "outlet": "The Guardian",
              "sourceBias": "Lean Left",
              "sourceReliability": "high",
              "bias": "Lean Left",
              "alignment": "Lean Left",
              "alignmentBasis": "source-default-fallback: no article alignment cues; source prior=Lean Left",
              "confidence": "high",
              "reliability": "high",
              "reliabilityBasis": "source-prior=high; article-text: no reliability modifier cues",
              "ratingMethod": "deterministic-local-article-heuristic-v2"
            }
          ],
          "summaryMethod": "deterministic-multi-source-mini-story-fallback-v1",
          "summaryFallbackReason": "lm-studio-summary-http-error: 400: {     \"error\": {         \"message\": \"No models loaded. Please load a model in the developer page or use the 'lms load' command.\",         \"type\":; retryError=lm-studio-summary-http-error: 400: {     \"error\": {         \"message\": \"No models loaded. Please load a mod; summaryBatchSize=1; chunkIndexes=[12]",
          "imageUrl": "https://i.guim.co.uk/img/media/cbe331faa3d00be216f17783e27b0d3f588f3678/202_0_1767_1414/master/1767.jpg?width=140&quality=85&auto=format&fit=max&s=eedf5bbad37333eab990324e08ee1783",
          "imageAlt": "UFC 6 review: a bloody, brilliant MMA fighting game",
          "imageCredit": "The Guardian"
        },
        {
          "title": "UK ministers lobby Trump to avert backlash against social media ban",
          "summary": "UK ministers lobby Trump to avert backlash against social media ban.\n\nNo 10 is worried about retaliation from White House over restrictions on under-16s’ internet use Ministers have embarked on a concerted lobbying operation to prevent a backlash from the Trump administration to the under-16s social media ban announced by Keir Starmer.\n\nOfficials said they had spent weeks trying to reassure senior Trump officials and the US president himself that the rest.",
          "links": [
            {
              "url": "https://www.theguardian.com/media/2026/jun/15/uk-ministers-lobby-trump-backlash-social-media-ban",
              "source": "The Guardian Technology",
              "headline": "UK ministers lobby Trump to avert backlash against social media ban",
              "excerpt": "No 10 is worried about retaliation from White House over restrictions on under-16s’ internet use Ministers have embarked on a concerted lobbying operation to prevent a backlash from the Trump administration to the under-16s social media ban announced by Keir Starmer. Officials said they had spent weeks trying to reassure senior Trump officials and the US president himself that the rest",
              "imageUrl": "https://i.guim.co.uk/img/media/fb178c151445976f565168e6c3737574c1dd5ca3/169_132_5741_4595/master/5741.jpg?width=140&quality=85&auto=format&fit=max&s=7449f5a2784628a874d7bea9a68b8d8c",
              "imageAlt": "UK ministers lobby Trump to avert backlash against social media ban",
              "outlet": "The Guardian",
              "sourceBias": "Lean Left",
              "sourceReliability": "high",
              "bias": "Lean Left",
              "alignment": "Lean Left",
              "alignmentBasis": "source-default-fallback: no article alignment cues; source prior=Lean Left",
              "confidence": "high",
              "reliability": "high",
              "reliabilityBasis": "source-prior=high; article-text raises reliability: (reuters|associated press|ap news|court documents|officials said|according to)",
              "ratingMethod": "deterministic-local-article-heuristic-v2"
            }
          ],
          "summaryMethod": "deterministic-multi-source-mini-story-fallback-v1",
          "summaryFallbackReason": "lm-studio-summary-http-error: 400: {     \"error\": {         \"message\": \"No models loaded. Please load a model in the developer page or use the 'lms load' command.\",         \"type\":; retryError=lm-studio-summary-http-error: 400: {     \"error\": {         \"message\": \"No models loaded. Please load a mod; summaryBatchSize=1; chunkIndexes=[13]",
          "imageUrl": "https://i.guim.co.uk/img/media/fb178c151445976f565168e6c3737574c1dd5ca3/169_132_5741_4595/master/5741.jpg?width=140&quality=85&auto=format&fit=max&s=7449f5a2784628a874d7bea9a68b8d8c",
          "imageAlt": "UK ministers lobby Trump to avert backlash against social media ban",
          "imageCredit": "The Guardian"
        },
        {
          "title": "The best power banks and battery packs in the UK for reliable charging on the go, tested",
          "summary": "The best power banks and battery packs in the UK for reliable charging on the go, tested. Forever running out of juice?\n\nTop up your battery-powered devices with our expert picks, from tiny smartphone chargers to super speedy models • The best iPhones: which Apple smartphone is right for you It’s disempowering when your smartphone, laptop or other important gadget runs out of battery.\n\nWith the flash of a graphic or a plaintive bleep, we lose a way to entertain our.",
          "links": [
            {
              "url": "https://www.theguardian.com/thefilter/2025/apr/10/best-power-banks-portable-chargers-battery-uk",
              "source": "The Guardian Technology",
              "headline": "The best power banks and battery packs in the UK for reliable charging on the go, tested",
              "excerpt": "Forever running out of juice? Top up your battery-powered devices with our expert picks, from tiny smartphone chargers to super speedy models • The best iPhones: which Apple smartphone is right for you It’s disempowering when your smartphone, laptop or other important gadget runs out of battery. With the flash of a graphic or a plaintive bleep, we lose a way to entertain our",
              "imageUrl": "https://i.guim.co.uk/img/media/0e99fc9ffe619dbd24bb45a4581c89bccd061ea4/0_0_5000_4000/master/5000.jpg?width=140&quality=85&auto=format&fit=max&s=8f3c860e8ca19111032f2f0c021e84c1",
              "imageAlt": "The best power banks and battery packs in the UK for reliable charging on the go, tested",
              "outlet": "The Guardian",
              "sourceBias": "Lean Left",
              "sourceReliability": "high",
              "bias": "Lean Left",
              "alignment": "Lean Left",
              "alignmentBasis": "source-default-fallback: no article alignment cues; source prior=Lean Left",
              "confidence": "high",
              "reliability": "high",
              "reliabilityBasis": "source-prior=high; article-text: no reliability modifier cues",
              "ratingMethod": "deterministic-local-article-heuristic-v2"
            }
          ],
          "summaryMethod": "deterministic-multi-source-mini-story-fallback-v1",
          "summaryFallbackReason": "lm-studio-summary-http-error: 400: {     \"error\": {         \"message\": \"No models loaded. Please load a model in the developer page or use the 'lms load' command.\",         \"type\":; retryError=lm-studio-summary-http-error: 400: {     \"error\": {         \"message\": \"No models loaded. Please load a mod; summaryBatchSize=1; chunkIndexes=[14]",
          "imageUrl": "https://i.guim.co.uk/img/media/0e99fc9ffe619dbd24bb45a4581c89bccd061ea4/0_0_5000_4000/master/5000.jpg?width=140&quality=85&auto=format&fit=max&s=8f3c860e8ca19111032f2f0c021e84c1",
          "imageAlt": "The best power banks and battery packs in the UK for reliable charging on the go, tested",
          "imageCredit": "The Guardian"
        },
        {
          "title": "Readers reply: Experts say we should use passkeys, but can a smartphone pin really be safer than a password?",
          "summary": "Readers reply: Experts say we should use passkeys, but can a smartphone pin really be safer than a password?.\n\nThe long-running series in which readers answer other readers’ questions on subjects ranging from trivial flights of fancy to profound scientific and philosophical concepts This week’s question: Is ‘ripen at home’ fruit the supermarkets’ idea of a joke?\n\nI’ve been struggling to get my head around the idea that a passkey, which can be a pin on your phone, or f.",
          "links": [
            {
              "url": "https://www.theguardian.com/lifeandstyle/2026/jun/14/readers-reply-experts-say-we-should-use-passkeys-but-can-a-smartphone-pin-really-be-safer-than-a-password",
              "source": "The Guardian Technology",
              "headline": "Readers reply: Experts say we should use passkeys, but can a smartphone pin really be safer than a password?",
              "excerpt": "The long-running series in which readers answer other readers’ questions on subjects ranging from trivial flights of fancy to profound scientific and philosophical concepts This week’s question: Is ‘ripen at home’ fruit the supermarkets’ idea of a joke? I’ve been struggling to get my head around the idea that a passkey, which can be a pin on your phone, or f",
              "imageUrl": "https://i.guim.co.uk/img/media/6fdc1325cf2b6330895bfda1c6df4d1f49c84424/1376_0_6880_5504/master/6880.jpg?width=140&quality=85&auto=format&fit=max&s=561769d939669e21ca68f70a722e1770",
              "imageAlt": "Readers reply: Experts say we should use passkeys, but can a smartphone pin really be safer than a password?",
              "outlet": "The Guardian",
              "sourceBias": "Lean Left",
              "sourceReliability": "high",
              "bias": "Lean Left",
              "alignment": "Lean Left",
              "alignmentBasis": "source-default-fallback: no article alignment cues; source prior=Lean Left",
              "confidence": "high",
              "reliability": "high",
              "reliabilityBasis": "source-prior=high; article-text: no reliability modifier cues",
              "ratingMethod": "deterministic-local-article-heuristic-v2"
            }
          ],
          "summaryMethod": "deterministic-multi-source-mini-story-fallback-v1",
          "summaryFallbackReason": "lm-studio-summary-http-error: 400: {     \"error\": {         \"message\": \"No models loaded. Please load a model in the developer page or use the 'lms load' command.\",         \"type\":; retryError=lm-studio-summary-http-error: 400: {     \"error\": {         \"message\": \"No models loaded. Please load a mod; summaryBatchSize=1; chunkIndexes=[15]",
          "imageUrl": "https://i.guim.co.uk/img/media/6fdc1325cf2b6330895bfda1c6df4d1f49c84424/1376_0_6880_5504/master/6880.jpg?width=140&quality=85&auto=format&fit=max&s=561769d939669e21ca68f70a722e1770",
          "imageAlt": "Readers reply: Experts say we should use passkeys, but can a smartphone pin really be safer than a password?",
          "imageCredit": "The Guardian"
        }
      ]
    },
    {
      "name": "Asia Pacific",
      "stories": [
        {
          "title": "Gatchalian thanks Villanueva, Escudero over their ‘statesmanship’",
          "summary": "Gatchalian thanks Villanueva, Escudero over their ‘statesmanship’. MANILA, Philippines — Newly elected Senate President Sherwin “Win” Gatchalian on Wednesday recognized the statesmanship shown by senators previously aligned with the current minority bloc, particularly Senators Joel Villanueva and Francis “Chiz” Escudero, for showing up during the special session.\n\nGatchalian sent his praise as the Senate had been in an impasse for weeks, as. Rappler: Gatchalian is new Senate President | The wRap.\n\nRappler reports that today’s headlines: Win Gatchalian, Chiz Escudero, Robin Padilla.",
          "links": [
            {
              "url": "https://newsinfo.inquirer.net/2248355/gatchalian-thanks-villanueva-escudero-over-their-statesmanship",
              "source": "Philippine Daily Inquirer",
              "headline": "Gatchalian thanks Villanueva, Escudero over their ‘statesmanship’",
              "excerpt": "MANILA, Philippines — Newly elected Senate President Sherwin “Win” Gatchalian on Wednesday recognized the statesmanship shown by senators previously aligned with the current minority bloc, particularly Senators Joel Villanueva and Francis “Chiz” Escudero, for showing up during the special session. Gatchalian sent his praise as the Senate had been in an impasse for weeks, as",
              "imageUrl": "https://newsinfo.inquirer.net/files/2026/06/1237462.jpeg",
              "imageAlt": "Gatchalian thanks Villanueva, Escudero over their ‘statesmanship’",
              "outlet": "Philippine Daily Inquirer",
              "sourceBias": "Center",
              "sourceReliability": "medium",
              "bias": "Center",
              "alignment": "Center",
              "alignmentBasis": "source-default-fallback: no article alignment cues; source prior=Center",
              "confidence": "medium",
              "reliability": "medium",
              "reliabilityBasis": "source-prior=medium; article-text: no reliability modifier cues",
              "ratingMethod": "deterministic-local-article-heuristic-v2"
            },
            {
              "url": "https://www.rappler.com/video/daily-wrap/june-17-2026/",
              "source": "Rappler World",
              "headline": "Gatchalian is new Senate President",
              "excerpt": "Today’s headlines: Win Gatchalian, Chiz Escudero, Robin Padilla",
              "imageUrl": "https://www.rappler.com/tachyon/2026/06/THE-WRAP-LS-MAIN-16.jpg",
              "imageAlt": "Gatchalian is new Senate President",
              "outlet": "Rappler",
              "sourceBias": "Center",
              "sourceReliability": "medium",
              "bias": "Center",
              "alignment": "Center",
              "alignmentBasis": "source-default-fallback: no article alignment cues; source prior=Center",
              "confidence": "medium",
              "reliability": "medium",
              "reliabilityBasis": "source-prior=medium; article-text: no reliability modifier cues",
              "ratingMethod": "deterministic-local-article-heuristic-v2"
            }
          ],
          "summaryMethod": "deterministic-multi-source-mini-story-fallback-v1",
          "summaryFallbackReason": "lm-studio-summary-http-error: 400: {     \"error\": {         \"message\": \"No models loaded. Please load a model in the developer page or use the 'lms load' command.\",         \"type\":; retryError=lm-studio-summary-http-error: 400: {     \"error\": {         \"message\": \"No models loaded. Please load a mod; summaryBatchSize=1; chunkIndexes=[16]",
          "imageUrl": "https://newsinfo.inquirer.net/files/2026/06/1237462.jpeg",
          "imageAlt": "Gatchalian thanks Villanueva, Escudero over their ‘statesmanship’",
          "imageCredit": "Philippine Daily Inquirer"
        },
        {
          "title": "CA confirms 5 generals after half-month delay",
          "summary": "CA confirms 5 generals after half-month delay. MANILA, Philippines – The Committee on Appointments (CA) confirmed on Wednesday the promotion of five generals from the Armed Forces of the Philippines (AFP).\n\nThis comes over two weeks after the confirmation of the five senior military officers was put on hold on June 1 due to the lack of senators elected to the CA.\n\nRappler: Generals caught in Senate ‘war’ finally get long-awaited promotion. Rappler reports that after weeks of delays brought about by the paralysis in the Senate, five senior officers of the Armed Forces of the Philippines were finally confirmed to their new posts.",
          "links": [
            {
              "url": "https://newsinfo.inquirer.net/2248084/ca-confirms-5-generals-after-half-month-delay",
              "source": "Philippine Daily Inquirer",
              "headline": "CA confirms 5 generals after half-month delay",
              "excerpt": "MANILA, Philippines – The Committee on Appointments (CA) confirmed on Wednesday the promotion of five generals from the Armed Forces of the Philippines (AFP). This comes over two weeks after the confirmation of the five senior military officers was put on hold on June 1 due to the lack of senators elected to the CA.",
              "imageUrl": "https://newsinfo.inquirer.net/files/2026/06/20260617NJO-23.jpg",
              "imageAlt": "CA confirms 5 generals after half-month delay",
              "outlet": "Philippine Daily Inquirer",
              "sourceBias": "Center",
              "sourceReliability": "medium",
              "bias": "Center",
              "alignment": "Center",
              "alignmentBasis": "source-default-fallback: no article alignment cues; source prior=Center",
              "confidence": "high",
              "reliability": "high",
              "reliabilityBasis": "source-prior=medium; article-text raises reliability: (data|study|report|filing|statement|interview|confirmed|verified)",
              "ratingMethod": "deterministic-local-article-heuristic-v2"
            },
            {
              "url": "https://www.rappler.com/newsbreak/inside-track/five-generals-promotion-delay-june-17-2026/",
              "source": "Rappler World",
              "headline": "Generals caught in Senate ‘war’ finally get long-awaited promotion",
              "excerpt": "After weeks of delays brought about by the paralysis in the Senate, five senior officers of the Armed Forces of the Philippines were finally confirmed to their new posts",
              "imageUrl": "https://www.rappler.com/tachyon/2025/05/newsbreak-inside-track.jpeg",
              "imageAlt": "Generals caught in Senate ‘war’ finally get long-awaited promotion",
              "outlet": "Rappler",
              "sourceBias": "Center",
              "sourceReliability": "medium",
              "bias": "Center",
              "alignment": "Center",
              "alignmentBasis": "source-default-fallback: no article alignment cues; source prior=Center",
              "confidence": "high",
              "reliability": "high",
              "reliabilityBasis": "source-prior=medium; article-text raises reliability: (data|study|report|filing|statement|interview|confirmed|verified)",
              "ratingMethod": "deterministic-local-article-heuristic-v2"
            }
          ],
          "summaryMethod": "deterministic-multi-source-mini-story-fallback-v1",
          "summaryFallbackReason": "lm-studio-summary-http-error: 400: {     \"error\": {         \"message\": \"No models loaded. Please load a model in the developer page or use the 'lms load' command.\",         \"type\":; retryError=lm-studio-summary-http-error: 400: {     \"error\": {         \"message\": \"No models loaded. Please load a mod; summaryBatchSize=1; chunkIndexes=[17]",
          "imageUrl": "https://newsinfo.inquirer.net/files/2026/06/20260617NJO-23.jpg",
          "imageAlt": "CA confirms 5 generals after half-month delay",
          "imageCredit": "Philippine Daily Inquirer"
        },
        {
          "title": "WATCH: Congress holds special session (part 2) | July 17, 2026",
          "summary": "WATCH: Congress holds special session (part 2) | July 17, 2026. MANILA, Philippines – Lawmakers resume session as they tackle key national issues that demand urgent legislative action outside the regular calendar.\n\nCongress convened in special session on Wednesday morning following President Ferdinand Marcos Jr.’s call for lawmakers to tackle priority legislation, including the proposd Assistance to Individuals in Crisis Situations (AICS) and the anti-political dynasty.",
          "links": [
            {
              "url": "https://newsinfo.inquirer.net/2248120/watch-congress-holds-special-session-part-2-july-17-2026",
              "source": "Philippine Daily Inquirer",
              "headline": "WATCH: Congress holds special session (part 2)",
              "excerpt": "MANILA, Philippines – Lawmakers resume session as they tackle key national issues that demand urgent legislative action outside the regular calendar. Congress convened in special session on Wednesday morning following President Ferdinand Marcos Jr.’s call for lawmakers to tackle priority legislation, including the proposd Assistance to Individuals in Crisis Situations (AICS) and the anti-political dynasty",
              "imageUrl": "https://newsinfo.inquirer.net/files/2026/06/WATCH-Congress-holds-special-session-part-2-July-17-2026.png",
              "imageAlt": "WATCH: Congress holds special session (part 2) | July 17, 2026",
              "outlet": "Philippine Daily Inquirer",
              "sourceBias": "Center",
              "sourceReliability": "medium",
              "bias": "Center",
              "alignment": "Center",
              "alignmentBasis": "source-default-fallback: no article alignment cues; source prior=Center",
              "confidence": "medium",
              "reliability": "medium",
              "reliabilityBasis": "source-prior=medium; article-text: no reliability modifier cues",
              "ratingMethod": "deterministic-local-article-heuristic-v2"
            }
          ],
          "summaryMethod": "deterministic-multi-source-mini-story-fallback-v1",
          "summaryFallbackReason": "lm-studio-summary-http-error: 400: {     \"error\": {         \"message\": \"No models loaded. Please load a model in the developer page or use the 'lms load' command.\",         \"type\":; retryError=lm-studio-summary-http-error: 400: {     \"error\": {         \"message\": \"No models loaded. Please load a mod; summaryBatchSize=1; chunkIndexes=[18]",
          "imageUrl": "https://newsinfo.inquirer.net/files/2026/06/WATCH-Congress-holds-special-session-part-2-July-17-2026.png",
          "imageAlt": "WATCH: Congress holds special session (part 2) | July 17, 2026",
          "imageCredit": "Philippine Daily Inquirer"
        },
        {
          "title": "PCSO: No jackpot winners in June 17 lotto draws",
          "summary": "PCSO: No jackpot winners in June 17 lotto draws. MANILA, Philippines—No bettor won the jackpot prizes in the Grand Lotto 6/55 and MegaLotto 6/45 draws conducted Wednesday, June 17, according to the Philippine Charity Sweepstakes Office (PCSO).\n\nGrand Lotto 6/55 produced the winning combination 55-31-46-37-48-01 for a jackpot worth ₱45 million.\n\nNo ticket matched all six numbers. MegaLotto 6/45 yielded the winning combination 34-35-09-10-19-32.",
          "links": [
            {
              "url": "https://newsinfo.inquirer.net/2248292/pcso-no-jackpot-winners-in-june-17-lotto-draws",
              "source": "Philippine Daily Inquirer",
              "headline": "PCSO: No jackpot winners in June 17 lotto draws",
              "excerpt": "MANILA, Philippines—No bettor won the jackpot prizes in the Grand Lotto 6/55 and MegaLotto 6/45 draws conducted Wednesday, June 17, according to the Philippine Charity Sweepstakes Office (PCSO). Grand Lotto 6/55 produced the winning combination 55-31-46-37-48-01 for a jackpot worth ₱45 million. No ticket matched all six numbers. MegaLotto 6/45 yielded the winning combination 34-35-09-10-19-32",
              "imageUrl": "https://newsinfo.inquirer.net/files/2025/05/lotto-pcso.jpeg",
              "imageAlt": "PCSO: No jackpot winners in June 17 lotto draws",
              "outlet": "Philippine Daily Inquirer",
              "sourceBias": "Center",
              "sourceReliability": "medium",
              "bias": "Center",
              "alignment": "Center",
              "alignmentBasis": "source-default-fallback: no article alignment cues; source prior=Center",
              "confidence": "high",
              "reliability": "high",
              "reliabilityBasis": "source-prior=medium; article-text raises reliability: (reuters|associated press|ap news|court documents|officials said|according to)",
              "ratingMethod": "deterministic-local-article-heuristic-v2"
            }
          ],
          "summaryMethod": "deterministic-multi-source-mini-story-fallback-v1",
          "summaryFallbackReason": "lm-studio-summary-http-error: 400: {     \"error\": {         \"message\": \"No models loaded. Please load a model in the developer page or use the 'lms load' command.\",         \"type\":; retryError=lm-studio-summary-http-error: 400: {     \"error\": {         \"message\": \"No models loaded. Please load a mod; summaryBatchSize=1; chunkIndexes=[19]",
          "imageUrl": "https://newsinfo.inquirer.net/files/2025/05/lotto-pcso.jpeg",
          "imageAlt": "PCSO: No jackpot winners in June 17 lotto draws",
          "imageCredit": "Philippine Daily Inquirer"
        },
        {
          "title": "DepEd ensures ARAL funds go directly to teachers serving as tutors",
          "summary": "DepEd ensures ARAL funds go directly to teachers serving as tutors. MANILA, Philippines —The Department of Education (DepEd) is taking steps to ensure that funds from the Academic Recovery and Accessible Learning (ARAL) Program will directly reach teachers and educators serving as tutors nationwide.\n\nAccording to a DepEd statement issued on Wednesday, Education Secretary Sonny Angara stressed that the ARAL Program shows his department’s firm commitment.",
          "links": [
            {
              "url": "https://newsinfo.inquirer.net/2248243/deped-ensures-aral-funds-go-directly-to-teachers-serving-as-tutors",
              "source": "Philippine Daily Inquirer",
              "headline": "DepEd ensures ARAL funds go directly to teachers serving as tutors",
              "excerpt": "MANILA, Philippines —The Department of Education (DepEd) is taking steps to ensure that funds from the Academic Recovery and Accessible Learning (ARAL) Program will directly reach teachers and educators serving as tutors nationwide. According to a DepEd statement issued on Wednesday, Education Secretary Sonny Angara stressed that the ARAL Program shows his department’s firm commitment",
              "imageUrl": "https://newsinfo.inquirer.net/files/2026/06/TeacherInClass-17June2026.jpg",
              "imageAlt": "DepEd ensures ARAL funds go directly to teachers serving as tutors",
              "outlet": "Philippine Daily Inquirer",
              "sourceBias": "Center",
              "sourceReliability": "medium",
              "bias": "Center",
              "alignment": "Center",
              "alignmentBasis": "source-default-fallback: no article alignment cues; source prior=Center",
              "confidence": "high",
              "reliability": "high",
              "reliabilityBasis": "source-prior=medium; article-text raises reliability: (reuters|associated press|ap news|court documents|officials said|according to), (data|study|report|filing|statement|interview|confirmed|verified)",
              "ratingMethod": "deterministic-local-article-heuristic-v2"
            }
          ],
          "summaryMethod": "deterministic-multi-source-mini-story-fallback-v1",
          "summaryFallbackReason": "lm-studio-summary-http-error: 400: {     \"error\": {         \"message\": \"No models loaded. Please load a model in the developer page or use the 'lms load' command.\",         \"type\":; retryError=lm-studio-summary-http-error: 400: {     \"error\": {         \"message\": \"No models loaded. Please load a mod; summaryBatchSize=1; chunkIndexes=[20]",
          "imageUrl": "https://newsinfo.inquirer.net/files/2026/06/TeacherInClass-17June2026.jpg",
          "imageAlt": "DepEd ensures ARAL funds go directly to teachers serving as tutors",
          "imageCredit": "Philippine Daily Inquirer"
        }
      ]
    },
    {
      "name": "Business / Finance",
      "stories": [
        {
          "title": "Social media’s next evolution: user-controlled algorithms",
          "summary": "Social media’s next evolution: user-controlled algorithms. Social media feeds are becoming more customizable as platforms like Threads, Instagram, and TikTok introduce tools that let users directly influence the algorithms powering their recommendations.",
          "links": [
            {
              "url": "https://techcrunch.com/2026/06/17/social-medias-next-evolution-user-controlled-algorithms/",
              "source": "TechCrunch",
              "headline": "Social media’s next evolution: user-controlled algorithms",
              "excerpt": "Social media feeds are becoming more customizable as platforms like Threads, Instagram, and TikTok introduce tools that let users directly influence the algorithms powering their recommendations.",
              "imageUrl": "https://techcrunch.com/wp-content/uploads/2024/06/social-media-icons.jpg?resize=1200,798",
              "imageAlt": "Social media’s next evolution: user-controlled algorithms",
              "outlet": "TechCrunch",
              "sourceBias": "Center",
              "sourceReliability": "medium",
              "bias": "Center",
              "alignment": "Center",
              "alignmentBasis": "source-default-fallback: no article alignment cues; source prior=Center",
              "confidence": "medium",
              "reliability": "medium",
              "reliabilityBasis": "source-prior=medium; article-text: no reliability modifier cues",
              "ratingMethod": "deterministic-local-article-heuristic-v2"
            }
          ],
          "summaryMethod": "deterministic-multi-source-mini-story-fallback-v1",
          "summaryFallbackReason": "lm-studio-summary-http-error: 400: {     \"error\": {         \"message\": \"No models loaded. Please load a model in the developer page or use the 'lms load' command.\",         \"type\":; retryError=lm-studio-summary-http-error: 400: {     \"error\": {         \"message\": \"No models loaded. Please load a mod; summaryBatchSize=1; chunkIndexes=[21]",
          "imageUrl": "https://techcrunch.com/wp-content/uploads/2024/06/social-media-icons.jpg?resize=1200,798",
          "imageAlt": "Social media’s next evolution: user-controlled algorithms",
          "imageCredit": "TechCrunch"
        },
        {
          "title": "How the fight over US datacenters is scrambling this state’s politics: ‘We don’t want it’",
          "summary": "How the fight over US datacenters is scrambling this state’s politics: ‘We don’t want it’.\n\nJosh Shapiro, Pennsylvania’s governor, squares off with state lawmakers over the facilities powering an AI boom A controversial haunted house near Philadelphia, Pennsylvania , taps into its dark history every fall to scare tens of thousands of visitors.\n\nIn 1968, a local news station documented.",
          "links": [
            {
              "url": "https://www.theguardian.com/technology/2026/jun/16/pennsylvania-datacenters-debate-politicians",
              "source": "The Guardian Technology",
              "headline": "How the fight over US datacenters is scrambling this state’s politics: ‘We don’t want it’",
              "excerpt": "Josh Shapiro, Pennsylvania’s governor, squares off with state lawmakers over the facilities powering an AI boom A controversial haunted house near Philadelphia, Pennsylvania , taps into its dark history every fall to scare tens of thousands of visitors. In 1968, a local news station documented",
              "imageUrl": "https://i.guim.co.uk/img/media/44ac79819d18b911c53cb6926918bd64ac4d6973/464_0_4640_3712/master/4640.jpg?width=140&quality=85&auto=format&fit=max&s=70080639c1217663f712c96f2d1c95e3",
              "imageAlt": "How the fight over US datacenters is scrambling this state’s politics: ‘We don’t want it’",
              "outlet": "The Guardian",
              "sourceBias": "Lean Left",
              "sourceReliability": "high",
              "bias": "Lean Left",
              "alignment": "Lean Left",
              "alignmentBasis": "source-default-fallback: no article alignment cues; source prior=Lean Left",
              "confidence": "high",
              "reliability": "high",
              "reliabilityBasis": "source-prior=high; article-text: no reliability modifier cues",
              "ratingMethod": "deterministic-local-article-heuristic-v2"
            }
          ],
          "summaryMethod": "deterministic-multi-source-mini-story-fallback-v1",
          "summaryFallbackReason": "lm-studio-summary-http-error: 400: {     \"error\": {         \"message\": \"No models loaded. Please load a model in the developer page or use the 'lms load' command.\",         \"type\":; retryError=lm-studio-summary-http-error: 400: {     \"error\": {         \"message\": \"No models loaded. Please load a mod; summaryBatchSize=1; chunkIndexes=[22]",
          "imageUrl": "https://i.guim.co.uk/img/media/44ac79819d18b911c53cb6926918bd64ac4d6973/464_0_4640_3712/master/4640.jpg?width=140&quality=85&auto=format&fit=max&s=70080639c1217663f712c96f2d1c95e3",
          "imageAlt": "How the fight over US datacenters is scrambling this state’s politics: ‘We don’t want it’",
          "imageCredit": "The Guardian"
        },
        {
          "title": "13 Father’s Day gadget gifts your dad won’t stop talking about, based on raves from real dads",
          "summary": "13 Father’s Day gadget gifts your dad won’t stop talking about, based on raves from real dads. Skip the token tie and get him a gift he’ll still be telling people about years from now The very best Father’s Day deals and gifts for dads, grandfathers, and dads to be <a href=\"https://www.theguardian.com/global/2025/sep/09/sign-up-to-the-filter-us-our-newsletter-guide-to-buying-fe.",
          "links": [
            {
              "url": "https://www.theguardian.com/thefilter-us/2026/jun/14/fathers-day-tech-gadgets-dads",
              "source": "The Guardian Technology",
              "headline": "13 Father’s Day gadget gifts your dad won’t stop talking about, based on raves from real dads",
              "excerpt": "Skip the token tie and get him a gift he’ll still be telling people about years from now The very best Father’s Day deals and gifts for dads, grandfathers, and dads to be <a href=\"https://www.theguardian.com/global/2025/sep/09/sign-up-to-the-filter-us-our-newsletter-guide-to-buying-fe",
              "imageUrl": "https://i.guim.co.uk/img/media/80f9306edd93458ed9a636cbb34440d3a8e913a2/0_0_1548_1238/master/1548.jpg?width=140&quality=85&auto=format&fit=max&s=8dfca7ebde7a2377c13a36e870e7870f",
              "imageAlt": "13 Father’s Day gadget gifts your dad won’t stop talking about, based on raves from real dads",
              "outlet": "The Guardian",
              "sourceBias": "Lean Left",
              "sourceReliability": "high",
              "bias": "Lean Left",
              "alignment": "Lean Left",
              "alignmentBasis": "source-default-fallback: no article alignment cues; source prior=Lean Left",
              "confidence": "high",
              "reliability": "high",
              "reliabilityBasis": "source-prior=high; article-text: no reliability modifier cues",
              "ratingMethod": "deterministic-local-article-heuristic-v2"
            }
          ],
          "summaryMethod": "deterministic-multi-source-mini-story-fallback-v1",
          "summaryFallbackReason": "lm-studio-summary-http-error: 400: {     \"error\": {         \"message\": \"No models loaded. Please load a model in the developer page or use the 'lms load' command.\",         \"type\":; retryError=lm-studio-summary-http-error: 400: {     \"error\": {         \"message\": \"No models loaded. Please load a mod; summaryBatchSize=1; chunkIndexes=[23]",
          "imageUrl": "https://i.guim.co.uk/img/media/80f9306edd93458ed9a636cbb34440d3a8e913a2/0_0_1548_1238/master/1548.jpg?width=140&quality=85&auto=format&fit=max&s=8dfca7ebde7a2377c13a36e870e7870f",
          "imageAlt": "13 Father’s Day gadget gifts your dad won’t stop talking about, based on raves from real dads",
          "imageCredit": "The Guardian"
        },
        {
          "title": "Andrew Hastie compares AI to cold-war nuclear arms race and warns Australia may fall behind",
          "summary": "Andrew Hastie compares AI to cold-war nuclear arms race and warns Australia may fall behind. Liberal MP says Australia risks sovereignty and strategic independence being ‘constrained by the AI superpowers reshaping the global order’ Get our breaking news email , free app or daily news podcast Liberal MP Andrew Hastie says Australia should dramatically s.",
          "links": [
            {
              "url": "https://www.theguardian.com/australia-news/2026/jun/15/andrew-hastie-ai-artificial-intelligence-power-cold-war-nuclear-arms-race-comparison-australia",
              "source": "The Guardian Technology",
              "headline": "Andrew Hastie compares AI to cold-war nuclear arms race and warns Australia may fall behind",
              "excerpt": "Liberal MP says Australia risks sovereignty and strategic independence being ‘constrained by the AI superpowers reshaping the global order’ Get our breaking news email , free app or daily news podcast Liberal MP Andrew Hastie says Australia should dramatically s",
              "imageUrl": "https://i.guim.co.uk/img/media/fcf718c822f5b914247cb985836dc460501e4aab/390_0_4421_3537/master/4421.jpg?width=140&quality=85&auto=format&fit=max&s=ecc975f3eac80f712b2d3294ef9fac17",
              "imageAlt": "Andrew Hastie compares AI to cold-war nuclear arms race and warns Australia may fall behind",
              "outlet": "The Guardian",
              "sourceBias": "Lean Left",
              "sourceReliability": "high",
              "bias": "Lean Left",
              "alignment": "Lean Left",
              "alignmentBasis": "source-default-fallback: no article alignment cues; source prior=Lean Left",
              "confidence": "high",
              "reliability": "high",
              "reliabilityBasis": "source-prior=high; article-text: no reliability modifier cues",
              "ratingMethod": "deterministic-local-article-heuristic-v2"
            }
          ],
          "summaryMethod": "deterministic-multi-source-mini-story-fallback-v1",
          "summaryFallbackReason": "lm-studio-summary-http-error: 400: {     \"error\": {         \"message\": \"No models loaded. Please load a model in the developer page or use the 'lms load' command.\",         \"type\":; retryError=lm-studio-summary-http-error: 400: {     \"error\": {         \"message\": \"No models loaded. Please load a mod; summaryBatchSize=1; chunkIndexes=[24]",
          "imageUrl": "https://i.guim.co.uk/img/media/fcf718c822f5b914247cb985836dc460501e4aab/390_0_4421_3537/master/4421.jpg?width=140&quality=85&auto=format&fit=max&s=ecc975f3eac80f712b2d3294ef9fac17",
          "imageAlt": "Andrew Hastie compares AI to cold-war nuclear arms race and warns Australia may fall behind",
          "imageCredit": "The Guardian"
        },
        {
          "title": "Online racism is significantly affecting mental health, First Nations people say: ‘It’s like carrying a bully in your pocket’",
          "summary": "Online racism is significantly affecting mental health, First Nations people say: ‘It’s like carrying a bully in your pocket’. Australian Human Rights Commission has called for a digital duty of care to prevent social media algorithms from incentivising ‘racist’ content Get our breaking news email , free app or daily news podcast For the past week and half, the social media feeds of man.",
          "links": [
            {
              "url": "https://www.theguardian.com/australia-news/2026/jun/13/online-racism-mental-health-first-nations-australians-social-media-ntwnfb",
              "source": "The Guardian Technology",
              "headline": "Online racism is significantly affecting mental health, First Nations people say: ‘It’s like carrying a bully in your pocket’",
              "excerpt": "Australian Human Rights Commission has called for a digital duty of care to prevent social media algorithms from incentivising ‘racist’ content Get our breaking news email , free app or daily news podcast For the past week and half, the social media feeds of man",
              "imageUrl": "https://i.guim.co.uk/img/media/efbcbbc2b3b03aaa8767d121ee395cae77bdcfed/648_0_5790_4633/master/5790.jpg?width=140&quality=85&auto=format&fit=max&s=d10ea3c58e93097883ae653edf6d3736",
              "imageAlt": "Online racism is significantly affecting mental health, First Nations people say: ‘It’s like carrying a bully in your pocket’",
              "outlet": "The Guardian",
              "sourceBias": "Lean Left",
              "sourceReliability": "high",
              "bias": "Lean Left",
              "alignment": "Lean Left",
              "alignmentBasis": "source-default-fallback: no article alignment cues; source prior=Lean Left",
              "confidence": "high",
              "reliability": "high",
              "reliabilityBasis": "source-prior=high; article-text: no reliability modifier cues",
              "ratingMethod": "deterministic-local-article-heuristic-v2"
            }
          ],
          "summaryMethod": "deterministic-multi-source-mini-story-fallback-v1",
          "summaryFallbackReason": "lm-studio-summary-http-error: 400: {     \"error\": {         \"message\": \"No models loaded. Please load a model in the developer page or use the 'lms load' command.\",         \"type\":; retryError=lm-studio-summary-http-error: 400: {     \"error\": {         \"message\": \"No models loaded. Please load a mod; summaryBatchSize=1; chunkIndexes=[25]",
          "imageUrl": "https://i.guim.co.uk/img/media/efbcbbc2b3b03aaa8767d121ee395cae77bdcfed/648_0_5790_4633/master/5790.jpg?width=140&quality=85&auto=format&fit=max&s=d10ea3c58e93097883ae653edf6d3736",
          "imageAlt": "Online racism is significantly affecting mental health, First Nations people say: ‘It’s like carrying a bully in your pocket’",
          "imageCredit": "The Guardian"
        }
      ]
    }
  ]
}
